cn/__init__.py
cn/xiuxius/__init__.py
cn/xiuxius/uselesslib/__init__.py
cn/xiuxius/uselesslib/bool.py
cn/xiuxius/uselesslib/fun.py
cn/xiuxius/uselesslib/int.py
cn/xiuxius/uselesslib/str.py
cn/xiuxius/uselesslib/util.py
py_uselesslib-1.0.1.dist-info/licenses/LICENSE
py_uselesslib-1.0.1.dist-info/METADATA
py_uselesslib-1.0.1.dist-info/WHEEL
py_uselesslib-1.0.1.dist-info/top_level.txt
py_uselesslib-1.0.1.dist-info/RECORD
