Metadata-Version: 2.4
Name: Py-UselessLib
Version: 1.0.1
Summary: A useless Python library
Author-email: XiaoXiu <me@xiuxius.cn>
License-Expression: MIT
Project-URL: Homepage, https://github.com/SH-XiaoXiu/py-uselesslib
Classifier: Programming Language :: Python :: 3
Classifier: Operating System :: OS Independent
Requires-Python: >=3.6
License-File: LICENSE
Dynamic: license-file
